MANIFEST.in
README.rst
requirements.txt
setup.cfg
setup.py
kotti_pdf/__init__.py
kotti_pdf/__init__.pyc
kotti_pdf/fanstatic.py
kotti_pdf/fanstatic.pyc
kotti_pdf/interfaces.py
kotti_pdf/interfaces.pyc
kotti_pdf/resources.py
kotti_pdf/resources.pyc
kotti_pdf.egg-info/PKG-INFO
kotti_pdf.egg-info/SOURCES.txt
kotti_pdf.egg-info/dependency_links.txt
kotti_pdf.egg-info/entry_points.txt
kotti_pdf.egg-info/not-zip-safe
kotti_pdf.egg-info/requires.txt
kotti_pdf.egg-info/top_level.txt
kotti_pdf/alembic/README
kotti_pdf/alembic/env.py
kotti_pdf/alembic/env.pyc
kotti_pdf/alembic/script.py.mako
kotti_pdf/alembic/versions/.gitkeep
kotti_pdf/locale/.gitkeep
kotti_pdf/locale/README.me
kotti_pdf/static/scripts.js
kotti_pdf/static/scripts.min.js
kotti_pdf/static/styles.css
kotti_pdf/static/styles.min.css
kotti_pdf/templates/pdf.pt
kotti_pdf/tests/conftest.py
kotti_pdf/tests/test_functional.py
kotti_pdf/tests/test_resources.py
kotti_pdf/tests/test_view.py
kotti_pdf/views/__init__.py
kotti_pdf/views/__init__.pyc
kotti_pdf/views/edit.py
kotti_pdf/views/edit.pyc