Metadata-Version: 1.1
Name: kotti-pdf
Version: 0.4.3
Summary: PDF content type for Kotti
Home-page: https://github.com/b4oshany/kotti_pdf
Author: Oshane Bailey
Author-email: b4.oshany@gmail.com
License: BSD-derived (http://www.repoze.org/LICENSE.txt)
Keywords: kotti web cms wcms pylons pyramid sqlalchemy bootstrap pdf
Platform: UNKNOWN
Classifier: Programming Language :: Python
Classifier: Programming Language :: Python :: 2.7
Classifier: Framework :: Pylons
Classifier: Topic :: Internet :: WWW/HTTP
Classifier: Topic :: Internet :: WWW/HTTP :: Dynamic Content
Classifier: Topic :: Internet :: WWW/HTTP :: WSGI :: Application
Classifier: License :: Repoze Public License
